yapenv/.version
yapenv/__init__.py
yapenv/__main__.py
yapenv/cli.py
yapenv/config.py
yapenv/consts.py
yapenv/log.py
yapenv/utils.py
yapenv/cli/__init__.py
yapenv/cli/config.py
yapenv/cli/core.py
yapenv/cli/environment.py
yapenv/cli/options.py
yapenv/cli/pip.py
yapenv/cli/requirements.py
yapenv/cli/shell.py
yapenv/cli/virtualenv.py
yapenv/commands/__init__.py
yapenv/commands/environment.py
yapenv/commands/pip.py
yapenv/commands/shell.py
yapenv/commands/virtualenv.py
yapenv/templates/activate_yapenv_shell
yapenv/templates/config.yaml
yapenv/templates/config_with_requirements.yaml
yapenv-0.4.7.dist-info/LICENSE
yapenv-0.4.7.dist-info/METADATA
yapenv-0.4.7.dist-info/WHEEL
yapenv-0.4.7.dist-info/entry_points.txt
yapenv-0.4.7.dist-info/top_level.txt
yapenv-0.4.7.dist-info/RECORD
