Metadata-Version: 2.1
Name: yapenv
Version: 0.4.7
Summary: Yet another python environment
Home-page: https://github.com/LamaAni/yapenv
Author: Zav Shotan
Project-URL: Source, https://github.com/LamaAni/yapenv
Keywords: environment,venv,virtualenv,pyenv,poetry
License-File: LICENSE
Requires-Dist: click >=8.1.3
Requires-Dist: pyyaml >=6.0
Requires-Dist: python-dotenv >=0.20.0
Requires-Dist: virtualenv >=20.16.5
Requires-Dist: bole
